summarizer/__init__.py
summarizer/bert.py
summarizer/cluster_features.py
summarizer/sbert.py
summarizer/summary_processor.py
summarizer/util.py
summarizer/text_processors/__init__.py
summarizer/text_processors/coreference_handler.py
summarizer/text_processors/sentence_abc.py
summarizer/text_processors/sentence_handler.py
summarizer/transformer_embeddings/__init__.py
summarizer/transformer_embeddings/bert_embedding.py
summarizer/transformer_embeddings/sbert_embedding.py
tests/__init__.py
tests/test_coreference.py
tests/test_sbert.py
tests/test_sentence_handler.py
tests/test_summary_items.py
bert_extractive_summarizer-0.10.1.dist-info/LICENSE
bert_extractive_summarizer-0.10.1.dist-info/METADATA
bert_extractive_summarizer-0.10.1.dist-info/WHEEL
bert_extractive_summarizer-0.10.1.dist-info/top_level.txt
bert_extractive_summarizer-0.10.1.dist-info/RECORD
