Metadata-Version: 2.1
Name: bert-extractive-summarizer
Version: 0.10.1
Summary: Extractive Text Summarization with BERT
Home-page: https://github.com/dmmiller612/bert-extractive-summarizer
Author: Derek Miller
Author-email: dmmiller612@gmail.com
License: MIT
Download-URL: https://github.com/dmmiller612/bert-extractive-summarizer/archive/0.10.1.tar.gz
Keywords: bert,pytorch,machine learning,deep learning,extractive summarization,summary
Platform: UNKNOWN
License-File: LICENSE
